nodeorc/__init__.py
nodeorc/callbacks.py
nodeorc/db_ops.py
nodeorc/disk_mng.py
nodeorc/log.py
nodeorc/main.py
nodeorc/utils.py
nodeorc/water_level.py
nodeorc/db/__init__.py
nodeorc/db/base.py
nodeorc/db/callback.py
nodeorc/db/callback_url.py
nodeorc/db/camera_config.py
nodeorc/db/device.py
nodeorc/db/disk_management.py
nodeorc/db/profile.py
nodeorc/db/settings.py
nodeorc/db/task_form.py
nodeorc/db/time_series.py
nodeorc/db/video.py
nodeorc/db/water_level_settings.py
nodeorc/models/__init__.py
nodeorc/models/callback.py
nodeorc/models/callback_url.py
nodeorc/models/storage.py
nodeorc/models/subtask.py
nodeorc/models/task.py
nodeorc/tasks/__init__.py
nodeorc/tasks/local_task.py
nodeorc/tasks/task_form.py
nodeorc-0.2.4.dist-info/entry_points.txt
nodeorc-0.2.4.dist-info/licenses/LICENSE
nodeorc-0.2.4.dist-info/WHEEL
nodeorc-0.2.4.dist-info/METADATA
nodeorc-0.2.4.dist-info/RECORD
