Metadata-Version: 2.4
Name: nodeorc
Version: 0.2.4
Summary: NodeORC: Automated edge and cloud image-based discharge estimation with OpenRiverCam
Author-email: Hessel Winsemius <winsemius@rainbowsensing.com>
Requires-Python: >=3.9
Classifier: Development Status :: 4 - Beta
Classifier: Intended Audience :: Developers
Classifier: Intended Audience :: Science/Research
Classifier: Topic :: Scientific/Engineering :: Hydrology
Classifier: Topic :: Scientific/Engineering :: Image Processing
Classifier: License :: OSI Approved :: GNU Affero General Public License v3
Classifier: Programming Language :: Python :: 3
Classifier: Programming Language :: Python :: 3.9
Classifier: Programming Language :: Python :: 3.10
Classifier: Programming Language :: Python :: 3.11
Classifier: Programming Language :: Python :: 3.12
License-File: LICENSE
Requires-Dist: boto3
Requires-Dist: dask[distributed]
Requires-Dist: pika
Requires-Dist: pydantic==2.3.0
Requires-Dist: pyopenrivercam>=0.8.5
Requires-Dist: python-dotenv
Requires-Dist: requests
Requires-Dist: sqlalchemy
Requires-Dist: pytest ; extra == "test"
Requires-Dist: pytest-cov ; extra == "test"
Requires-Dist: pytest-lazy-fixtures ; extra == "test"
Requires-Dist: pytest-mock ; extra == "test"
Project-URL: Source, https://github.com/localdevices/nodeorc
Provides-Extra: test
